LICENSE
MANIFEST.in
README.md
lastbox.py
setup.py
lastbox.egg-info/PKG-INFO
lastbox.egg-info/SOURCES.txt
lastbox.egg-info/dependency_links.txt
lastbox.egg-info/entry_points.txt
lastbox.egg-info/top_level.txt