Metadata-Version: 1.1
Name: lastbox
Version: 0.2.0
Summary: Last.fm submission script for Rockbox' scrobbler.log
Home-page: https://github.com/Mendor/lastbox
Author: Nikita K.
Author-email: mendor@yuuzukiyo.net
License: MIT
Keywords: last.fm rockbox scrobbling
Platform: UNKNOWN
Classifier: Development Status :: 5 - Production/Stable
Classifier: Environment :: Console
Classifier: Intended Audience :: End Users/Desktop
Classifier: License :: OSI Approved :: MIT License
Classifier: Operating System :: MacOS :: MacOS X
Classifier: Operating System :: POSIX :: Linux
Classifier: Programming Language :: Python :: 2
Classifier: Programming Language :: Python :: 2 :: Only
Classifier: Topic :: Internet :: Log Analysis
Classifier: Topic :: Utilities
